setup.py
shinkenplugins/__init__.py
shinkenplugins.plugins.hydro_quebec.egg-info/PKG-INFO
shinkenplugins.plugins.hydro_quebec.egg-info/SOURCES.txt
shinkenplugins.plugins.hydro_quebec.egg-info/dependency_links.txt
shinkenplugins.plugins.hydro_quebec.egg-info/entry_points.txt
shinkenplugins.plugins.hydro_quebec.egg-info/namespace_packages.txt
shinkenplugins.plugins.hydro_quebec.egg-info/requires.txt
shinkenplugins.plugins.hydro_quebec.egg-info/top_level.txt
shinkenplugins/plugins/__init__.py
shinkenplugins/plugins/hydro_quebec/__init__.py
shinkenplugins/plugins/hydro_quebec/hydro_quebec.py